excepting/__init__.py
excepting/core/__init__.py
excepting/tests/__init__.py
excepting/tests/test_0.py
excepting-0.0.3.dist-info/licenses/LICENSE.txt
excepting-0.0.3.dist-info/METADATA
excepting-0.0.3.dist-info/WHEEL
excepting-0.0.3.dist-info/top_level.txt
excepting-0.0.3.dist-info/RECORD
