Metadata-Version: 2.4
Name: excepting
Version: 0.0.3
Summary: This project allows to capture exceptions easily.
Author-email: Johannes <johannes.programming@gmail.com>
License: The MIT License (MIT)
Project-URL: Download, https://pypi.org/project/excepting/#files
Project-URL: Index, https://pypi.org/project/excepting/
Project-URL: Source, https://github.com/johannes-programming/excepting/
Project-URL: Website, https://excepting.johannes-programming.online/
Classifier: Development Status :: 2 - Pre-Alpha
Classifier: License :: OSI Approved :: MIT License
Classifier: Natural Language :: English
Classifier: Operating System :: OS Independent
Classifier: Programming Language :: Python
Classifier: Programming Language :: Python :: 3
Classifier: Programming Language :: Python :: 3 :: Only
Classifier: Typing :: Typed
Requires-Python: >=3.11
License-File: LICENSE.txt
Dynamic: license-file
